tensormodel/__init__.py
tensormodel/nsfw/__init__.py
tensormodel/nsfw/_nsfw.py
tensormodel-0.1.0.dist-info/LICENSE
tensormodel-0.1.0.dist-info/METADATA
tensormodel-0.1.0.dist-info/WHEEL
tensormodel-0.1.0.dist-info/top_level.txt
tensormodel-0.1.0.dist-info/RECORD
